padar_features/__init__.py
padar_features/feature_extractor.py
padar_features/feature_set.py
padar_features/features/__init__.py
padar_features/features/accelerometer/__init__.py
padar_features/features/accelerometer/activation.py
padar_features/features/accelerometer/activity_count.py
padar_features/features/accelerometer/orientation.py
padar_features/features/accelerometer/spectrum.py
padar_features/features/accelerometer/stats.py
padar_features/features/accelerometer/tests/__init__.py
padar_features/features/accelerometer/tests/test_mean.py
padar_features/features/accelerometer/tests/test_orientation.py
padar_features/features/accelerometer/tests/test_spectrum.py
padar_features/features/gps/__init__.py
padar_features/libs/__init__.py
padar_features/libs/data_formatting/__init__.py
padar_features/libs/data_formatting/decorator.py
padar_features/libs/data_formatting/formatter.py
padar_features/libs/data_formatting/operator.py
padar_features/libs/data_formatting/parser.py
padar_features/libs/data_formatting/validator.py
padar_features/libs/signal_processing/__init__.py
padar_features/libs/signal_processing/detect_peaks.py
padar_features/libs/signal_processing/filters.py
padar_features/libs/signal_processing/signal_generator.py
padar_features/transformations/__init__.py
padar_features/transformations/accelerometer/__init__.py
padar_features/transformations/accelerometer/orientation.py
padar_features-0.3.0.dist-info/METADATA
padar_features-0.3.0.dist-info/RECORD
padar_features-0.3.0.dist-info/WHEEL
padar_features-0.3.0.dist-info/top_level.txt
