Metadata-Version: 2.1
Name: padar-features
Version: 0.3.0
Summary: Extension of feature computation to be used in padar package
Home-page: UNKNOWN
Author: UNKNOWN
Author-email: UNKNOWN
License: UNKNOWN
Platform: UNKNOWN
Requires-Dist: pandas (>=0.23.0)
Requires-Dist: numpy (>=1.15.1)
Requires-Dist: scipy (>=1.1.0)
Requires-Dist: dask[complete] (>=0.18.1)
Requires-Dist: bokeh (>=0.13.0)
Requires-Dist: padar-parallel (>=0.2.5)
Requires-Dist: padar-converter (>=0.2.17)
